{
  "id": "cinema-expert",
  "engineTemplate": "turn-based",
  "mode": "individual",
  "title": "خبير السينما",
  "author": "Imhotep Tech",
  "hasTimer": true,
  "defaultTimerSeconds": 30,
  "isTimerCustomizable": true,
  "allowElimination": false,
  "themeColor": "#e11d48",
  "logo": "🎬",
  "instructions": "هل أنت موسوعة سينمائية متحركة؟\n\nالعمر: +9 | المدة: 20+ دقيقة | اللاعبين: +2\n\nكيفية اللعب:\n1. سيظهر تحدي سينمائي على الشاشة (مثال: اذكر 3 أفلام لفلان).\n2. الجميع يلعب في نفس الوقت! كن أول من يذكر العدد المطلوب من الأفلام أو الشخصيات.\n3. أسرع شخص يكمل التحدي قبل البقية وفي الوقت المحدد يربح النقطة.\n4. ثانية واحدة قد تكون الفارق بينك وبين لقب 'الخبير السينمائي'!",
  "turnStrategy": "open",
  "allowPass": true,
  "cardsFile": "cinema-expert-cards.json"
}